henipipe/__init__.py
henipipe/__main__.py
henipipe/auc.py
henipipe/henipipe.py
henipipe/pyWriter.py
henipipe/samComp.py
henipipe/samTobed.py
henipipe/data/environs.json
henipipe/data/genomes.json
henipipe/scripts/SEACR_1.1.R
henipipe/scripts/SEACR_1.1.sh
henipipe/scripts/SEACR_1.3.R
henipipe/scripts/SEACR_1.3.sh
henipipe-2.4.14.dist-info/LICENSE
henipipe-2.4.14.dist-info/METADATA
henipipe-2.4.14.dist-info/WHEEL
henipipe-2.4.14.dist-info/entry_points.txt
henipipe-2.4.14.dist-info/top_level.txt
henipipe-2.4.14.dist-info/RECORD
