Metadata-Version: 2.1
Name: henipipe
Version: 2.4.14
Summary: A python wrapper for fast and parallel processing of sequencing data using CutnRun or CutnTag
Home-page: https://github.com/scfurl/henipipe.git
Author: Scott Furlan
Author-email: scottfurlan@gmail.com
License: UNKNOWN
Platform: UNKNOWN
Classifier: Programming Language :: Python :: 3
Classifier: License :: OSI Approved :: MIT License
Classifier: Operating System :: OS Independent
Requires-Python: >=2.5
Requires-Dist: six (>=1)
